odoo/addons/fieldservice_website_sale_extra_step/README.rst
odoo/addons/fieldservice_website_sale_extra_step/__init__.py
odoo/addons/fieldservice_website_sale_extra_step/__manifest__.py
odoo/addons/fieldservice_website_sale_extra_step/i18n/ca.po
odoo/addons/fieldservice_website_sale_extra_step/i18n/es.po
odoo/addons/fieldservice_website_sale_extra_step/i18n/fieldservice_website_sale_extra_step.pot
odoo/addons/fieldservice_website_sale_extra_step/models/__init__.py
odoo/addons/fieldservice_website_sale_extra_step/models/sale_order.py
odoo/addons/fieldservice_website_sale_extra_step/readme/CONTRIBUTORS.rst
odoo/addons/fieldservice_website_sale_extra_step/readme/DESCRIPTION.rst
odoo/addons/fieldservice_website_sale_extra_step/readme/USAGE.rst
odoo/addons/fieldservice_website_sale_extra_step/static/description/icon.png
odoo/addons/fieldservice_website_sale_extra_step/static/description/index.html
odoo/addons/fieldservice_website_sale_extra_step/tests/__init__.py
odoo/addons/fieldservice_website_sale_extra_step/tests/test_fieldservice_website_sale_extra_step.py
odoo_addon_fieldservice_website_sale_extra_step-15.0.1.0.0.1.dist-info/METADATA
odoo_addon_fieldservice_website_sale_extra_step-15.0.1.0.0.1.dist-info/WHEEL
odoo_addon_fieldservice_website_sale_extra_step-15.0.1.0.0.1.dist-info/top_level.txt
odoo_addon_fieldservice_website_sale_extra_step-15.0.1.0.0.1.dist-info/RECORD
